pretix/__init__.py
pretix/__main__.py
pretix/celery_app.py
pretix/sentry.py
pretix/settings.py
pretix/urls.py
pretix/wsgi.py
pretix/api/__init__.py
pretix/api/exception.py
pretix/api/middleware.py
pretix/api/models.py
pretix/api/oauth.py
pretix/api/signals.py
pretix/api/urls.py
pretix/api/webhooks.py
pretix/api/auth/__init__.py
pretix/api/auth/device.py
pretix/api/auth/devicesecurity.py
pretix/api/auth/permission.py
pretix/api/auth/token.py
pretix/api/migrations/0001_initial.py
pretix/api/migrations/0002_auto_20180604_1120.py
pretix/api/migrations/0003_webhook_webhookcall_webhookeventlistener.py
pretix/api/migrations/0004_auto_20190405_1048.py
pretix/api/migrations/0005_auto_20191028_1541.py
pretix/api/migrations/__init__.py
pretix/api/serializers/__init__.py
pretix/api/serializers/cart.py
pretix/api/serializers/checkin.py
pretix/api/serializers/event.py
pretix/api/serializers/exporters.py
pretix/api/serializers/fields.py
pretix/api/serializers/i18n.py
pretix/api/serializers/item.py
pretix/api/serializers/order.py
pretix/api/serializers/organizer.py
pretix/api/serializers/settings.py
pretix/api/serializers/voucher.py
pretix/api/serializers/waitinglist.py
pretix/api/serializers/webhooks.py
pretix/api/views/__init__.py
pretix/api/views/cart.py
pretix/api/views/checkin.py
pretix/api/views/device.py
pretix/api/views/event.py
pretix/api/views/exporters.py
pretix/api/views/item.py
pretix/api/views/oauth.py
pretix/api/views/order.py
pretix/api/views/organizer.py
pretix/api/views/upload.py
pretix/api/views/user.py
pretix/api/views/version.py
pretix/api/views/voucher.py
pretix/api/views/waitinglist.py
pretix/api/views/webhooks.py
pretix/base/__init__.py
pretix/base/auth.py
pretix/base/banlist.py
pretix/base/cache.py
pretix/base/channels.py
pretix/base/context.py
pretix/base/decimal.py
pretix/base/email.py
pretix/base/exporter.py
pretix/base/i18n.py
pretix/base/invoice.py
pretix/base/metrics.py
pretix/base/middleware.py
pretix/base/notifications.py
pretix/base/orderimport.py
pretix-3.16.0.dist-info/METADATA
pretix-3.16.0.dist-info/WHEEL
pretix-3.16.0.dist-info/top_level.txt
pretix-3.16.0.dist-info/RECORD
