Metadata-Version: 2.1
Name: pretix
Version: 3.16.0
Summary: Reinventing presales, one ticket at a time
Home-page: https://pretix.eu
Author: Raphael Michel
Author-email: mail@raphaelmichel.de
License: Apache License 2.0
Keywords: tickets web shop ecommerce
Platform: UNKNOWN
Classifier: Development Status :: 5 - Production/Stable
Classifier: Intended Audience :: Developers
Classifier: Intended Audience :: Other Audience
Classifier: Topic :: Internet :: WWW/HTTP :: Dynamic Content
Classifier: Environment :: Web Environment
Classifier: License :: OSI Approved :: Apache Software License
Classifier: Programming Language :: Python :: 3.6
Classifier: Programming Language :: Python :: 3.7
Classifier: Programming Language :: Python :: 3.8
Classifier: Framework :: Django :: 3.0
Requires-Python: >=3.6
Requires-Dist: Django (==3.0.*,>=3.0.9)
Requires-Dist: djangorestframework (==3.11.*)
Requires-Dist: python-dateutil (==2.8.*)
Requires-Dist: isoweek
Requires-Dist: requests (==2.24.*)
Requires-Dist: pytz
Requires-Dist: django-bootstrap3 (==12.0.*)
Requires-Dist: django-formset-js-improved (==0.5.0.2)
Requires-Dist: django-compressor (==2.4.*)
Requires-Dist: django-hierarkey (==1.0.*,>=1.0.4)
Requires-Dist: django-filter (==2.2.*)
Requires-Dist: django-scopes (==1.2.*)
Requires-Dist: reportlab (>=3.5.18)
Requires-Dist: Pillow (==7.*)
Requires-Dist: PyPDF2 (==1.26.*)
Requires-Dist: django-libsass (==0.8)
Requires-Dist: libsass (==0.20.*)
Requires-Dist: django-otp (==0.7.*,>=0.7.5)
Requires-Dist: webauthn (==0.4.*)
Requires-Dist: python-u2flib-server (==4.*)
Requires-Dist: django-formtools (==2.2)
Requires-Dist: celery (==4.4.*)
Requires-Dist: kombu (==4.6.*)
Requires-Dist: django-statici18n (==1.9.*)
Requires-Dist: inlinestyler (==0.2.*)
Requires-Dist: BeautifulSoup4 (==4.8.*)
Requires-Dist: slimit
Requires-Dist: lxml
Requires-Dist: static3 (==0.7.*)
Requires-Dist: dj-static
Requires-Dist: csscompressor
Requires-Dist: django-markup
Requires-Dist: markdown (==3.3.*)
Requires-Dist: bleach (==3.3.*)
Requires-Dist: sentry-sdk (==0.14.*)
Requires-Dist: babel
Requires-Dist: paypalrestsdk (==1.13.*)
Requires-Dist: pycparser (==2.13)
Requires-Dist: django-redis (==4.11.*)
Requires-Dist: redis (==3.4.*)
Requires-Dist: stripe (==2.42.*)
Requires-Dist: chardet (<3.1.0,>=3.0.2)
Requires-Dist: mt-940 (==3.2)
Requires-Dist: django-i18nfield (>=1.7.0)
Requires-Dist: django-jsonfallback (>=2.1.2)
Requires-Dist: psycopg2-binary
Requires-Dist: tqdm (==4.*)
Requires-Dist: vobject (==0.9.*)
Requires-Dist: pycountry
Requires-Dist: django-countries (>=6.0)
Requires-Dist: pyuca
Requires-Dist: defusedcsv (>=1.1.0)
Requires-Dist: vat-moss-forked (==2020.3.20.0.11.0)
Requires-Dist: django-localflavor (>=2.2)
Requires-Dist: jsonschema
Requires-Dist: django-hijack (<2.2.0,>=2.1.10)
Requires-Dist: openpyxl (==3.0.*)
Requires-Dist: django-oauth-toolkit (==1.2.*)
Requires-Dist: oauthlib (==3.1.*)
Requires-Dist: django-phonenumber-field (==4.0.*)
Requires-Dist: phonenumberslite (==8.11.*)
Requires-Dist: python-bidi (==0.4.*)
Requires-Dist: arabic-reshaper (==2.0.15)
Requires-Dist: packaging
Requires-Dist: tlds (>=2020041600)
Requires-Dist: text-unidecode (==1.*)
Requires-Dist: protobuf (==3.13.*)
Requires-Dist: cryptography (>=3.4.2)
Requires-Dist: sepaxml (==2.4.*,>=2.4.1)
Provides-Extra: dev
Requires-Dist: django-debug-toolbar (==2.1) ; extra == 'dev'
Requires-Dist: pycodestyle (==2.5.*) ; extra == 'dev'
Requires-Dist: pyflakes (==2.1.*) ; extra == 'dev'
Requires-Dist: flake8 (==3.7.*) ; extra == 'dev'
Requires-Dist: pep8-naming ; extra == 'dev'
Requires-Dist: coveralls ; extra == 'dev'
Requires-Dist: coverage ; extra == 'dev'
Requires-Dist: pytest (==6.*) ; extra == 'dev'
Requires-Dist: pytest-django (==4.*) ; extra == 'dev'
Requires-Dist: pytest-xdist (==1.31.*) ; extra == 'dev'
Requires-Dist: isort ; extra == 'dev'
Requires-Dist: pytest-mock (==2.0.*) ; extra == 'dev'
Requires-Dist: pytest-rerunfailures (==9.*) ; extra == 'dev'
Requires-Dist: responses ; extra == 'dev'
Requires-Dist: potypo ; extra == 'dev'
Requires-Dist: freezegun ; extra == 'dev'
Provides-Extra: memcached
Requires-Dist: pylibmc ; extra == 'memcached'
Provides-Extra: mysql
Requires-Dist: mysqlclient ; extra == 'mysql'
